README.md
setup.cfg
setup.py
bamboo/__init__.py
bamboo/config.py
bamboo/dataframe.py
bamboo/exceptions.py
bamboo/fields.py
bamboo/orm.py
bamboo/queries.py
bamboo/utils.py
elasticsearch_bamboo.egg-info/PKG-INFO
elasticsearch_bamboo.egg-info/SOURCES.txt
elasticsearch_bamboo.egg-info/dependency_links.txt
elasticsearch_bamboo.egg-info/requires.txt
elasticsearch_bamboo.egg-info/top_level.txt