Metadata-Version: 2.1
Name: elasticsearch-bamboo
Version: 0.3.2
Summary: DataFrame interface for ElasticSearch
Home-page: https://github.com/juvoinc/bamboo
Author: Aaron Mangum
Author-email: aaron.mangum@juvo.com
License: Mozilla Public License 2.0 (MPL 2.0)
Download-URL: https://github.com/juvoinc/bamboo/archive/0.3.2.tar.gz
Keywords: elasticsearch,dataframe,pandas
Platform: UNKNOWN
Classifier: Development Status :: 5 - Production/Stable
Classifier: Intended Audience :: Developers
Classifier: License :: OSI Approved :: Mozilla Public License 2.0 (MPL 2.0)
Classifier: Topic :: Software Development
Classifier: Topic :: Utilities
Classifier: Programming Language :: Python
Classifier: Programming Language :: Python :: 2.7
Classifier: Programming Language :: Python :: 3
Requires-Python: >=2.7
Provides-Extra: test
Provides-Extra: pandas
Provides-Extra: dev
